{"advanced_cli.md":"BD8JfewP","advanced_docs.md":"CtzHGm4w","advanced_frameworks.md":"CTpLUhZ7","advanced_gotchas.md":"B9QHyjOB","advanced_libraries.md":"BdX5JxvE","advanced_loading.md":"DSowj9zq","advanced_scoping.md":"B3FO8Lj8","advanced_ssr.md":"DPD-9OHY","advanced_typescript.md":"B_PYGQXJ","api_index.md":"DQ2FPx2b","components_events.md":"BCp-Dpa0","components_lifecycle.md":"BGmOxUsy","components_methods.md":"Btf-I9Hl","components_options.md":"7kx9ySam","components_props.md":"BFpzXnYP","components_styles.md":"4wRWAIsH","components_templates.md":"CzF_dFjp","components_terminology.md":"CVH3IFgJ","examples_index.md":"B8ktq4lu","index.md":"DzYVX_XE","start_index.md":"MqvaaNm7"}
