{"about_code-of-conduct.md":"3TNkvRX8","about_privacy.md":"CJWsXWbE","about_team.md":"DjbBTtdz","advanced_cli.md":"BfZ-ykZm","advanced_docs.md":"Cyu3HlA6","advanced_faq.md":"Da_ZvrFL","advanced_frameworks.md":"Cmh27FMy","advanced_gotchas.md":"CaD9Rjk_","advanced_libraries.md":"C3_stNuG","advanced_loading.md":"B3HqtV6s","advanced_mcp.md":"CNI10B29","advanced_scoping.md":"DqsyeAGv","advanced_ssr.md":"DYYOYAgW","advanced_typescript.md":"CnXCtABF","api_index.md":"CvbtcMDa","components_events.md":"DC5iD8Oe","components_lifecycle.md":"CAGea0dW","components_methods.md":"B-JZRdqq","components_mixins.md":"D2-5HFTD","components_options.md":"BstH-K5y","components_overview.md":"DsAzioDd","components_props.md":"CoNzQ4Lr","components_styles.md":"BQiaDKhH","components_templates.md":"DqnyKF5K","examples_index.md":"CXZianJD","index.md":"BKE3kRBe","playground_index.md":"C00XCExx","start_index.md":"B5OJyrVn"}
