{"about_code-of-conduct.md":"D5uu2uI1","about_privacy.md":"BtQ83Gbh","about_sponsor.md":"iW3Grx_7","about_team.md":"BE_EIwWc","advanced_cli.md":"C3eV0JE8","advanced_docs.md":"DkyoLDqZ","advanced_faq.md":"Djyl74JZ","advanced_frameworks.md":"B_qxTD9h","advanced_gotchas.md":"CcN9v1Zd","advanced_libraries.md":"CXpCRYU2","advanced_loading.md":"CTZJs4CX","advanced_mcp.md":"DoR1wRBD","advanced_scoping.md":"A7nC4RgH","advanced_ssr.md":"kMObEtBj","advanced_typescript.md":"B0CZsC7F","api_index.md":"BC1CSel-","components_events.md":"Bq86y20r","components_lifecycle.md":"Bc4zreX1","components_methods.md":"DFKFhluT","components_mixins.md":"Ddeejy7S","components_options.md":"DrpCONDI","components_overview.md":"CTr0L_XT","components_props.md":"CZ9W657Y","components_rendering.md":"CayV3oiX","components_styles.md":"C-GlMRMW","components_templates.md":"BoW2YGtw","examples_index.md":"DFk2UBGz","examples_pre-rendered.md":"UbsE9uAE","index.md":"ChLdO_iK","playground_index.md":"BxSKYXfn","start_index.md":"DDnVX6Y-"}
