{"about_code-of-conduct.md":"BkYyoC0C","about_privacy.md":"CsOu3YnU","about_sponsor.md":"DOIKQS2n","about_team.md":"Wh1FX5c2","advanced_cli.md":"Bhtcma_t","advanced_docs.md":"CbBG6q_J","advanced_faq.md":"D0BpL9YT","advanced_frameworks.md":"Bu5N72ZF","advanced_gotchas.md":"CEp0xxRS","advanced_libraries.md":"L5JO7r0W","advanced_loading.md":"DLYpQ1wu","advanced_mcp.md":"5kTLL6sr","advanced_scoping.md":"BLdkHvT1","advanced_ssr.md":"DOFMi6aJ","advanced_typescript.md":"-rL_GRw-","api_index.md":"B7yv4Jgy","components_events.md":"DMF_kG34","components_lifecycle.md":"CRMw-uE2","components_methods.md":"Da7wKJfo","components_mixins.md":"BTq7IAxe","components_options.md":"DZADG-zp","components_overview.md":"nO-RzxFL","components_props.md":"k2jRlZFT","components_rendering.md":"BKzO5OtM","components_styles.md":"BiJd0SrN","components_templates.md":"Bkt_S44m","examples_index.md":"BgPI3RZl","examples_pre-rendered.md":"bbgMNM43","index.md":"DWIW5JeQ","playground_index.md":"lvrVCe98","start_index.md":"BA54tSfv"}
